PyTermUtils/PyTermUtils.py
PyTermUtils/__init__.py
PyTermUtils/utils_enum.py
PyTermUtils-0.0.0.dist-info/LICENSE
PyTermUtils-0.0.0.dist-info/METADATA
PyTermUtils-0.0.0.dist-info/WHEEL
PyTermUtils-0.0.0.dist-info/top_level.txt
PyTermUtils-0.0.0.dist-info/RECORD
