Metadata-Version: 2.1
Name: PyTermUtils
Version: 0.0.0
Summary: A Python library for ANSI color formatting for terminal/console output
Author-email: Amit Kumar <amitkr4538@gmail.com>
Project-URL: Homepage, https://github.com/amitkr000/PyTermUtils
Project-URL: Issues, https://github.com/amitkr000/PyTermUtils/issues
Classifier: Programming Language :: Python :: 3
Classifier: License :: OSI Approved :: MIT License
Classifier: Operating System :: OS Independent
Requires-Python: >=3.6
License-File: LICENSE
